{
  "id": "Unknown",
  "name": "Unknown",
  "studio": "",
  "description": "Unknown formats",
  "familyType": "GameX.Unknown.UnknownFamily, GameX",
  "samples": [
    "UnknownFamily.Sample.json"
  ],
  "games": {
    "*": {
      "archiveType": "GameX.Unknown.UnknownArchive, GameX"
    },
    "APP": {
      "name": "Application",
      "files": {
        "key": "Direct:%AppPath%"
      },
      "virtuals": {
        "testtri.gfx": null
      }
    },
    "CAT": {
      "name": "Catalog",
      "arc": "game:/main.yaml",
      "files": {
        "key": "Direct:%AppPath%/catalogs"
      }
    }
  }
}